rapix/__init__.py
rapix-0.0.1.dist-info/METADATA
rapix-0.0.1.dist-info/WHEEL
rapix-0.0.1.dist-info/entry_points.txt
rapix-0.0.1.dist-info/RECORD
