Metadata-Version: 2.4
Name: rapix
Version: 0.0.1
Summary: Cross-repository version coordination
Project-URL: Homepage, https://rapix.dev
Author: Bill Polson
License: MIT
Keywords: asset-management,pipeline,version-control,vfx
Classifier: Development Status :: 1 - Planning
Classifier: Intended Audience :: Developers
Classifier: License :: OSI Approved :: MIT License
Classifier: Programming Language :: Python :: 3
Classifier: Programming Language :: Python :: 3.10
Classifier: Programming Language :: Python :: 3.11
Classifier: Programming Language :: Python :: 3.12
Classifier: Programming Language :: Python :: 3.13
Requires-Python: >=3.10
